permutations/__init__.py
permutations/permutations.py
permutations-0.2.0.dist-info/LICENSE
permutations-0.2.0.dist-info/METADATA
permutations-0.2.0.dist-info/WHEEL
permutations-0.2.0.dist-info/top_level.txt
permutations-0.2.0.dist-info/RECORD
